Metadata-Version: 2.1
Name: hnzhu010506
Version: 0.0.1
Summary: A small example package
Home-page: UNKNOWN
Author: hnzhu2
Author-email: 1170618497@qq.com
License: UNKNOWN
Platform: UNKNOWN
Classifier: Programming Language :: Python :: 3
Classifier: License :: OSI Approved :: MIT License
Classifier: Operating System :: OS Independent
License-File: LICENSE.txt
Requires-Dist: albumentations (==1.0.3)
Requires-Dist: allure-combine (==1.0.6)
Requires-Dist: allure-pytest (==2.9.45)
Requires-Dist: allure-python-commons (==2.9.45)
Requires-Dist: appdirs (==1.4.4)
Requires-Dist: artifactory (==0.1.17)
Requires-Dist: asn1crypto (==1.5.1)
Requires-Dist: atomicwrites (==1.4.1)
Requires-Dist: attrs (==22.1.0)
Requires-Dist: bcrypt (==3.2.2)
Requires-Dist: beautifulsoup4 (==4.11.1)
Requires-Dist: bs4 (==0.0.1)
Requires-Dist: cached-property (==1.5.2)
Requires-Dist: certifi (==2022.6.15)
Requires-Dist: cffi (==1.15.1)
Requires-Dist: charset-normalizer (==2.0.12)
Requires-Dist: colorama (==0.4.4)
Requires-Dist: comtypes (==1.1.11)
Requires-Dist: cryptography (==37.0.0)
Requires-Dist: cycler (==0.11.0)
Requires-Dist: decorator (==4.4.2)
Requires-Dist: Deprecated (==1.2.13)
Requires-Dist: docker (==4.4.4)
Requires-Dist: docker-compose (==1.25.4)
Requires-Dist: dockerpty (==0.4.1)
Requires-Dist: docopt (==0.6.2)
Requires-Dist: et-xmlfile (==1.1.0)
Requires-Dist: facebook-wda (==1.4.6)
Requires-Dist: flatbuffers (==2.0)
Requires-Dist: gitdb2 (==2.0.6)
Requires-Dist: GitPython (==2.1.15)
Requires-Dist: hrpc (==1.0.9)
Requires-Dist: idna (==3.3)
Requires-Dist: imageio (==2.15.0)
Requires-Dist: importlib-metadata (==4.8.3)
Requires-Dist: importlib-resources (==5.4.0)
Requires-Dist: iniconfig (==1.1.1)
Requires-Dist: Jinja2 (==3.0.3)
Requires-Dist: jsonschema (==3.2.0)
Requires-Dist: kiwisolver (==1.3.1)
Requires-Dist: MarkupSafe (==2.0.1)
Requires-Dist: matplotlib (==3.3.4)
Requires-Dist: mss (==6.1.0)
Requires-Dist: networkx (==2.5.1)
Requires-Dist: nose (==1.3.7)
Requires-Dist: numpy (==1.19.5)
Requires-Dist: onnxruntime (==1.10.0)
Requires-Dist: openpyxl (==3.0.10)
Requires-Dist: packaging (==21.3)
Requires-Dist: pandas (==1.1.5)
Requires-Dist: paramiko (==2.11.0)
Requires-Dist: pathlib (==1.0.1)
Requires-Dist: Pillow (==8.4.0)
Requires-Dist: pixelmatch (==0.2.4)
Requires-Dist: pluggy (==1.0.0)
Requires-Dist: plumbum (==1.7.2)
Requires-Dist: poco (==0.99.1)
Requires-Dist: pocoui (==1.0.87)
Requires-Dist: protobuf (==4.21.0)
Requires-Dist: py (==1.11.0)
Requires-Dist: pyaml (==19.12.0)
Requires-Dist: pyasn1 (==0.4.8)
Requires-Dist: pycparser (==2.21)
Requires-Dist: pyee (==8.2.2)
Requires-Dist: PyGithub (==1.45)
Requires-Dist: PyJWT (==2.4.0)
Requires-Dist: PyNaCl (==1.5.0)
Requires-Dist: pyparsing (==3.0.7)
Requires-Dist: pypiwin32 (==223)
Requires-Dist: pyppeteer (==0.2.6)
Requires-Dist: pyrsistent (==0.18.0)
Requires-Dist: pytesseract (==0.3.8)
Requires-Dist: pytest-ordering (==0.6)
Requires-Dist: pytest-repeat (==0.9.1)
Requires-Dist: python-dateutil (==2.8.2)
Requires-Dist: python-gitlab (==1.15.0)
Requires-Dist: pytz (==2022.1)
Requires-Dist: PyWavelets (==1.1.1)
Requires-Dist: pywin32 (==227)
Requires-Dist: pywinauto (==0.6.3)
Requires-Dist: PyYAML (==5.3)
Requires-Dist: pyttsx3 (==2.90)
Requires-Dist: requests (==2.27.1)
Requires-Dist: retry (==0.9.2)
Requires-Dist: rpyc (==5.0.1)
Requires-Dist: scikit-image (==0.17.2)
Requires-Dist: scipy (==1.5.4)
Requires-Dist: six (==1.16.0)
Requires-Dist: smmap (==5.0.0)
Requires-Dist: smmap2 (==3.0.1)
Requires-Dist: soupsieve (==2.3.2.post1)
Requires-Dist: svn (==1.0.1)
Requires-Dist: texttable (==1.6.4)
Requires-Dist: tifffile (==2020.9.3)
Requires-Dist: tomli (==1.2.3)
Requires-Dist: tqdm (==4.64.0)
Requires-Dist: typing-extensions (==4.1.1)
Requires-Dist: urllib3 (==1.26.11)
Requires-Dist: websocket-client (==0.48.0)
Requires-Dist: websockets (==9.1)
Requires-Dist: wrapt (==1.14.1)
Requires-Dist: xlrd (==2.0.1)
Requires-Dist: zipp (==3.6.0)
